rafina/P3A_runner
rafina/__init__.py
rafina/__pydyn__.py
rafina/libboost_atomic.so.1.87.0
rafina/libboost_container.so.1.87.0
rafina/libboost_filesystem.so.1.87.0
rafina/libboost_graph.so.1.87.0
rafina/libboost_numpy310.so.1.87.0
rafina/libboost_python310.so.1.87.0
rafina/libboost_system.so.1.87.0
rafina/librafutility_mod.so
rafina/pyraf.so
rafina-0.0.9.dist-info/LICENSE.txt
rafina-0.0.9.dist-info/METADATA
rafina-0.0.9.dist-info/WHEEL
rafina-0.0.9.dist-info/top_level.txt
rafina-0.0.9.dist-info/RECORD
