Metadata-Version: 2.1
Name: rafina
Version: 0.0.9
Summary: Read content from RAF files: .raf and .dyn
Home-page: https://www.sintef.no
Author: ('Morten Grova',)
Author-email: ('Morten.Grova@sintef.no',)
License: BSD-3-Clause
Requires-Python: >=3.9
License-File: LICENSE.txt
Requires-Dist: numpy
